itu_r_468_weighting/__init__.py
itu_r_468_weighting/constants.py
itu_r_468_weighting/filter (conflicted copy 2019-09-21 132126).py
itu_r_468_weighting/filter.py
itu_r_468_weighting-2.0.3.dist-info/LICENSE
itu_r_468_weighting-2.0.3.dist-info/METADATA
itu_r_468_weighting-2.0.3.dist-info/PKG-INFO (conflicted copy 2019-09-21 132347)
itu_r_468_weighting-2.0.3.dist-info/WHEEL
itu_r_468_weighting-2.0.3.dist-info/top_level.txt
itu_r_468_weighting-2.0.3.dist-info/RECORD
