Metadata-Version: 2.1
Name: itu-r-468-weighting
Version: 2.0.3
Summary: A zero dependency Python ITU-R 468 noise weighting filter (1 kHz and 2 kHz)
Home-page: https://github.com/cinelexi/itu-r-468-weighting
Author: Alexis Michaltsis
Author-email: a.michaltsis@gmail.com
License: MIT
Keywords: ITU-R BS.468-4 SMPTE RP 2054:2010 noise weighting filter
Platform: UNKNOWN
Classifier: Intended Audience :: Developers
Classifier: Topic :: Multimedia :: Sound/Audio :: Analysis
Classifier: License :: OSI Approved :: MIT License
Classifier: Programming Language :: Python :: 3
Classifier: Programming Language :: Python :: 3.6
Requires-Python: >=3.6
